grun/__init__.py
grun/__main__.py
gpu_runner-0.0.7.dist-info/METADATA
gpu_runner-0.0.7.dist-info/WHEEL
gpu_runner-0.0.7.dist-info/entry_points.txt
gpu_runner-0.0.7.dist-info/top_level.txt
gpu_runner-0.0.7.dist-info/RECORD
