Metadata-Version: 2.1
Name: gpu-runner
Version: 0.0.7
Summary: Run a command requiring GPU resources
Home-page: https://github.com/cosmoquester/gpu-runner.git
Author: Sangjun Park
Requires-Python: >=3.7
Requires-Dist: filelock
Requires-Dist: nvidia-ml-py3
Requires-Dist: psutil
